fairyfly_therm/__init__.py
fairyfly_therm/__main__.py
fairyfly_therm/_extend_fairyfly.py
fairyfly_therm/config.json
fairyfly_therm/config.py
fairyfly_therm/result.py
fairyfly_therm/run.py
fairyfly_therm/writer.py
fairyfly_therm/_templates/Default.xml
fairyfly_therm/cli/__init__.py
fairyfly_therm/cli/setconfig.py
fairyfly_therm/cli/simulate.py
fairyfly_therm/cli/translate.py
fairyfly_therm/condition/__init__.py
fairyfly_therm/condition/_base.py
fairyfly_therm/condition/steadystate.py
fairyfly_therm/lib/__init__.py
fairyfly_therm/lib/_loadconditions.py
fairyfly_therm/lib/_loadgases.py
fairyfly_therm/lib/_loadmaterials.py
fairyfly_therm/lib/conditions.py
fairyfly_therm/lib/gases.py
fairyfly_therm/lib/materials.py
fairyfly_therm/material/__init__.py
fairyfly_therm/material/_base.py
fairyfly_therm/material/cavity.py
fairyfly_therm/material/dictutil.py
fairyfly_therm/material/gas.py
fairyfly_therm/material/solid.py
fairyfly_therm/material/xmlutil.py
fairyfly_therm/properties/__init__.py
fairyfly_therm/properties/boundary.py
fairyfly_therm/properties/model.py
fairyfly_therm/properties/shape.py
fairyfly_therm/simulation/__init__.py
fairyfly_therm/simulation/mesh.py
fairyfly_therm/simulation/parameter.py
fairyfly_therm-0.9.8.dist-info/licenses/LICENSE
fairyfly_therm-0.9.8.dist-info/METADATA
fairyfly_therm-0.9.8.dist-info/WHEEL
fairyfly_therm-0.9.8.dist-info/entry_points.txt
fairyfly_therm-0.9.8.dist-info/top_level.txt
fairyfly_therm-0.9.8.dist-info/RECORD
